psycaio/__init__.py
psycaio/conn.py
psycaio/conn_connect.py
psycaio/cursor.py
psycaio/utils.py
psycaio-0.3.dist-info/LICENSE
psycaio-0.3.dist-info/METADATA
psycaio-0.3.dist-info/WHEEL
psycaio-0.3.dist-info/top_level.txt
psycaio-0.3.dist-info/zip-safe
psycaio-0.3.dist-info/RECORD
