Metadata-Version: 2.1
Name: psycaio
Version: 0.3
Summary: Asyncio psycopg2 mixin
Home-page: https://github.com/blenq/psycaio
Author: Bart Lengkeek
Author-email: github@lengkeek.com
License: MIT License
Project-URL: Documentation, https://psycaio.readthedocs.io/
Project-URL: Code, https://github.com/blenq/psycaio
Project-URL: Issue Tracker, https://github.com/blenq/psycaio/issues
Keywords: asyncio,postgresql,psycopg2
Platform: any
Classifier: Framework :: AsyncIO
Classifier: Development Status :: 3 - Alpha
Classifier: Intended Audience :: Developers
Classifier: License :: OSI Approved :: MIT License
Classifier: Operating System :: OS Independent
Classifier: Programming Language :: Python :: 3
Classifier: Programming Language :: Python :: 3.6
Classifier: Programming Language :: Python :: 3.7
Classifier: Programming Language :: Python :: 3.8
Classifier: Topic :: Database
Classifier: Topic :: Database :: Front-Ends
Classifier: Topic :: Software Development
Classifier: Topic :: Software Development :: Libraries
Classifier: Topic :: Software Development :: Libraries :: Python Modules
Requires-Python: >=3.6
Requires-Dist: psycopg2 (>=2.7.0)
